DFW/__init__.py
DFW/predefine.py
DFW/preprocess.py
DFW/tools.py
DFW-1.0.2.dist-info/LICENSE
DFW-1.0.2.dist-info/METADATA
DFW-1.0.2.dist-info/WHEEL
DFW-1.0.2.dist-info/top_level.txt
DFW-1.0.2.dist-info/RECORD
